django_rest_oso/__init__.py
django_rest_oso/filters.py
django_rest_oso/permissions.py
django_rest_oso/serializers.py
django_rest_oso-0.1.0.dist-info/WHEEL
django_rest_oso-0.1.0.dist-info/METADATA
django_rest_oso-0.1.0.dist-info/RECORD
