Metadata-Version: 2.1
Name: django-rest-oso
Version: 0.1.0
Summary: Oso implementation for Django Rest.
Author: Javier Alonso Shannon
Author-email: javier.as@medicalwebexperts.com
Requires-Python: >=3.10,<4.0
Classifier: Programming Language :: Python :: 3
Classifier: Programming Language :: Python :: 3.10
Requires-Dist: Django (>=4.0,<5)
Requires-Dist: django-oso (>=0.26,<0.27)
Requires-Dist: djangorestframework (>=3.13,<4)
